coreapi/__init__.py
coreapi/auth.py
coreapi/client.py
coreapi/compat.py
coreapi/document.py
coreapi/exceptions.py
coreapi/utils.py
coreapi/__pycache__/__init__.cpython-33.pyc
coreapi/__pycache__/__init__.cpython-34.pyc
coreapi/__pycache__/__init__.cpython-35.pyc
coreapi/__pycache__/__init__.cpython-36.pyc
coreapi/__pycache__/auth.cpython-36.pyc
coreapi/__pycache__/client.cpython-33.pyc
coreapi/__pycache__/client.cpython-34.pyc
coreapi/__pycache__/client.cpython-35.pyc
coreapi/__pycache__/client.cpython-36.pyc
coreapi/__pycache__/compat.cpython-33.pyc
coreapi/__pycache__/compat.cpython-34.pyc
coreapi/__pycache__/compat.cpython-35.pyc
coreapi/__pycache__/compat.cpython-36.pyc
coreapi/__pycache__/document.cpython-33.pyc
coreapi/__pycache__/document.cpython-34.pyc
coreapi/__pycache__/document.cpython-35.pyc
coreapi/__pycache__/document.cpython-36.pyc
coreapi/__pycache__/exceptions.cpython-33.pyc
coreapi/__pycache__/exceptions.cpython-34.pyc
coreapi/__pycache__/exceptions.cpython-35.pyc
coreapi/__pycache__/exceptions.cpython-36.pyc
coreapi/__pycache__/utils.cpython-33.pyc
coreapi/__pycache__/utils.cpython-34.pyc
coreapi/__pycache__/utils.cpython-35.pyc
coreapi/__pycache__/utils.cpython-36.pyc
coreapi/codecs/__init__.py
coreapi/codecs/base.py
coreapi/codecs/corejson.py
coreapi/codecs/display.py
coreapi/codecs/download.py
coreapi/codecs/jsondata.py
coreapi/codecs/python.py
coreapi/codecs/text.py
coreapi/codecs/__pycache__/__init__.cpython-33.pyc
coreapi/codecs/__pycache__/__init__.cpython-34.pyc
coreapi/codecs/__pycache__/__init__.cpython-35.pyc
coreapi/codecs/__pycache__/__init__.cpython-36.pyc
coreapi/codecs/__pycache__/base.cpython-33.pyc
coreapi/codecs/__pycache__/base.cpython-34.pyc
coreapi/codecs/__pycache__/base.cpython-35.pyc
coreapi/codecs/__pycache__/base.cpython-36.pyc
coreapi/codecs/__pycache__/corejson.cpython-33.pyc
coreapi/codecs/__pycache__/corejson.cpython-34.pyc
coreapi-2.3.2.dist-info/DESCRIPTION.rst
coreapi-2.3.2.dist-info/METADATA
coreapi-2.3.2.dist-info/RECORD
coreapi-2.3.2.dist-info/WHEEL
coreapi-2.3.2.dist-info/entry_points.txt
coreapi-2.3.2.dist-info/metadata.json
coreapi-2.3.2.dist-info/top_level.txt
